[
    {
        "GPA":3.4,
        "A%":48,
        "B%":21,
        "C%":5,
        "D%":0,
        "F%":3,
        "Professor":"All"
    },
    {
        "GPA":3.12,
        "A%":30,
        "B%":25,
        "C%":3,
        "D%":0,
        "F%":5,
        "Professor":"Bellissard, Jean"
    },
    {
        "GPA":3.17,
        "A%":24,
        "B%":45,
        "C%":7,
        "D%":0,
        "F%":2,
        "Professor":"Bunimovich, Leonid"
    },
    {
        "GPA":4.0,
        "A%":100,
        "B%":0,
        "C%":0,
        "D%":0,
        "F%":0,
        "Professor":"Geronimo, Jeffrey"
    },
    {
        "GPA":3.7,
        "A%":73,
        "B%":10,
        "C%":10,
        "D%":0,
        "F%":0,
        "Professor":"Houdre, Christian"
    },
    {
        "GPA":3.34,
        "A%":42,
        "B%":13,
        "C%":17,
        "D%":0,
        "F%":0,
        "Professor":"Hurley, Katherine"
    },
    {
        "GPA":3.43,
        "A%":59,
        "B%":16,
        "C%":10,
        "D%":0,
        "F%":4,
        "Professor":"Koltchinskii, Vladimir"
    },
    {
        "GPA":3.75,
        "A%":73,
        "B%":16,
        "C%":4,
        "D%":0,
        "F%":0,
        "Professor":"Matzinger, Heinrich"
    },
    {
        "GPA":3.31,
        "A%":32,
        "B%":22,
        "C%":6,
        "D%":1,
        "F%":3,
        "Professor":"Tetali, Prasad"
    },
    {
        "GPA":3.42,
        "A%":50,
        "B%":19,
        "C%":0,
        "D%":0,
        "F%":7,
        "Professor":"Yu, Xing"
    }
]