[
    {
        "GPA":3.59,
        "A%":69,
        "B%":13,
        "C%":6,
        "D%":1,
        "F%":2,
        "Professor":"All"
    },
    {
        "GPA":3.0,
        "A%":0,
        "B%":100,
        "C%":0,
        "D%":0,
        "F%":0,
        "Professor":"Andrew, Alfred"
    },
    {
        "GPA":3.96,
        "A%":96,
        "B%":5,
        "C%":0,
        "D%":0,
        "F%":0,
        "Professor":"Baker, Matthew"
    },
    {
        "GPA":4.0,
        "A%":100,
        "B%":0,
        "C%":0,
        "D%":0,
        "F%":0,
        "Professor":"Basu, Saugata"
    },
    {
        "GPA":2.9,
        "A%":25,
        "B%":14,
        "C%":4,
        "D%":0,
        "F%":10,
        "Professor":"Bellissard, Jean"
    },
    {
        "GPA":3.0,
        "A%":0,
        "B%":100,
        "C%":0,
        "D%":0,
        "F%":0,
        "Professor":"Cain Jr, George"
    },
    {
        "GPA":4.0,
        "A%":100,
        "B%":0,
        "C%":0,
        "D%":0,
        "F%":0,
        "Professor":"Croot III, Ernest"
    },
    {
        "GPA":4.0,
        "A%":100,
        "B%":0,
        "C%":0,
        "D%":0,
        "F%":0,
        "Professor":"Etnyre, John"
    },
    {
        "GPA":4.0,
        "A%":100,
        "B%":0,
        "C%":0,
        "D%":0,
        "F%":0,
        "Professor":"Goldsztein, Guillermo"
    },
    {
        "GPA":2.0,
        "A%":0,
        "B%":0,
        "C%":100,
        "D%":0,
        "F%":0,
        "Professor":"Green, William"
    },
    {
        "GPA":4.0,
        "A%":100,
        "B%":0,
        "C%":0,
        "D%":0,
        "F%":0,
        "Professor":"Heil, Christopher"
    },
    {
        "GPA":3.13,
        "A%":63,
        "B%":5,
        "C%":7,
        "D%":3,
        "F%":13,
        "Professor":"Heitsch, Christine"
    },
    {
        "GPA":4.0,
        "A%":100,
        "B%":0,
        "C%":0,
        "D%":0,
        "F%":0,
        "Professor":"Lacey, Michael"
    },
    {
        "GPA":2.0,
        "A%":0,
        "B%":0,
        "C%":100,
        "D%":0,
        "F%":0,
        "Professor":"Landsberg, Joseph"
    },
    {
        "GPA":4.0,
        "A%":100,
        "B%":0,
        "C%":0,
        "D%":0,
        "F%":0,
        "Professor":"Lefton, Lew"
    },
    {
        "GPA":3.82,
        "A%":79,
        "B%":10,
        "C%":3,
        "D%":0,
        "F%":0,
        "Professor":"Leverson, Caitlin"
    },
    {
        "GPA":3.66,
        "A%":77,
        "B%":4,
        "C%":13,
        "D%":0,
        "F%":0,
        "Professor":"Leykin, Anton"
    },
    {
        "GPA":4.0,
        "A%":100,
        "B%":0,
        "C%":0,
        "D%":0,
        "F%":0,
        "Professor":"Loss, Michael"
    },
    {
        "GPA":3.0,
        "A%":0,
        "B%":100,
        "C%":0,
        "D%":0,
        "F%":0,
        "Professor":"Lubinsky, Doron"
    },
    {
        "GPA":4.0,
        "A%":100,
        "B%":0,
        "C%":0,
        "D%":0,
        "F%":0,
        "Professor":"Margalit, Dan"
    },
    {
        "GPA":3.34,
        "A%":30,
        "B%":30,
        "C%":3,
        "D%":3,
        "F%":0,
        "Professor":"McCuan, John"
    },
    {
        "GPA":3.33,
        "A%":53,
        "B%":33,
        "C%":7,
        "D%":7,
        "F%":0,
        "Professor":"Millman, Richard"
    },
    {
        "GPA":3.93,
        "A%":89,
        "B%":4,
        "C%":0,
        "D%":0,
        "F%":1,
        "Professor":"Morley, Thomas"
    },
    {
        "GPA":3.75,
        "A%":75,
        "B%":25,
        "C%":0,
        "D%":0,
        "F%":0,
        "Professor":"Nagle, Brendan"
    },
    {
        "GPA":2.67,
        "A%":40,
        "B%":0,
        "C%":0,
        "D%":0,
        "F%":20,
        "Professor":"Porter, Mason"
    },
    {
        "GPA":4.0,
        "A%":100,
        "B%":0,
        "C%":0,
        "D%":0,
        "F%":0,
        "Professor":"Shapira, Asaf"
    },
    {
        "GPA":3.64,
        "A%":62,
        "B%":25,
        "C%":2,
        "D%":1,
        "F%":0,
        "Professor":"Shenk, Ronald"
    },
    {
        "GPA":4.0,
        "A%":100,
        "B%":0,
        "C%":0,
        "D%":0,
        "F%":0,
        "Professor":"Thomas, Robin"
    },
    {
        "GPA":3.5,
        "A%":50,
        "B%":50,
        "C%":0,
        "D%":0,
        "F%":0,
        "Professor":"Ulmer, Douglas"
    },
    {
        "GPA":4.0,
        "A%":100,
        "B%":0,
        "C%":0,
        "D%":0,
        "F%":0,
        "Professor":"Wang, Yang"
    },
    {
        "GPA":3.83,
        "A%":71,
        "B%":6,
        "C%":1,
        "D%":0,
        "F%":1,
        "Professor":"Weiss, Howard"
    },
    {
        "GPA":3.0,
        "A%":50,
        "B%":0,
        "C%":50,
        "D%":0,
        "F%":0,
        "Professor":"Yu, Xing"
    }
]