[
    {
        "GPA":3.96,
        "A%":90,
        "B%":3,
        "C%":0,
        "D%":0,
        "F%":0,
        "Professor":"All"
    },
    {
        "GPA":3.96,
        "A%":80,
        "B%":1,
        "C%":0,
        "D%":0,
        "F%":1,
        "Professor":"Allvine, Fred"
    },
    {
        "GPA":3.94,
        "A%":94,
        "B%":6,
        "C%":0,
        "D%":0,
        "F%":0,
        "Professor":"Atasu, Atalay"
    },
    {
        "GPA":4.0,
        "A%":100,
        "B%":0,
        "C%":0,
        "D%":0,
        "F%":0,
        "Professor":"Beebe, Marshall"
    },
    {
        "GPA":4.0,
        "A%":100,
        "B%":0,
        "C%":0,
        "D%":0,
        "F%":0,
        "Professor":"Bennett, Nathan"
    },
    {
        "GPA":3.96,
        "A%":95,
        "B%":4,
        "C%":0,
        "D%":0,
        "F%":0,
        "Professor":"Berbari, Margaret"
    },
    {
        "GPA":4.0,
        "A%":74,
        "B%":0,
        "C%":0,
        "D%":0,
        "F%":0,
        "Professor":"Blum, Terry"
    },
    {
        "GPA":4.0,
        "A%":87,
        "B%":0,
        "C%":0,
        "D%":0,
        "F%":0,
        "Professor":"Bond, Samuel"
    },
    {
        "GPA":4.0,
        "A%":100,
        "B%":0,
        "C%":0,
        "D%":0,
        "F%":0,
        "Professor":"Branch SR, Barrington"
    },
    {
        "GPA":4.0,
        "A%":100,
        "B%":0,
        "C%":0,
        "D%":0,
        "F%":0,
        "Professor":"Braunstein, Mark"
    },
    {
        "GPA":4.0,
        "A%":100,
        "B%":0,
        "C%":0,
        "D%":0,
        "F%":0,
        "Professor":"Buchanan, Michael"
    },
    {
        "GPA":4.0,
        "A%":100,
        "B%":0,
        "C%":0,
        "D%":0,
        "F%":0,
        "Professor":"Burgess, Robert"
    },
    {
        "GPA":4.0,
        "A%":88,
        "B%":0,
        "C%":0,
        "D%":0,
        "F%":0,
        "Professor":"Byars, Lloyd"
    },
    {
        "GPA":3.9,
        "A%":80,
        "B%":10,
        "C%":0,
        "D%":0,
        "F%":0,
        "Professor":"Carroll, Timothy"
    },
    {
        "GPA":3.0,
        "A%":0,
        "B%":100,
        "C%":0,
        "D%":0,
        "F%":0,
        "Professor":"Carson, Jennifer"
    },
    {
        "GPA":4.0,
        "A%":100,
        "B%":0,
        "C%":0,
        "D%":0,
        "F%":0,
        "Professor":"Ceccagnoli, Marco"
    },
    {
        "GPA":4.0,
        "A%":100,
        "B%":0,
        "C%":0,
        "D%":0,
        "F%":0,
        "Professor":"Chakrabarti, Rajesh"
    },
    {
        "GPA":3.65,
        "A%":63,
        "B%":35,
        "C%":0,
        "D%":0,
        "F%":0,
        "Professor":"Challagalla, Goutam"
    },
    {
        "GPA":4.0,
        "A%":95,
        "B%":0,
        "C%":0,
        "D%":0,
        "F%":0,
        "Professor":"Chang, Yih-Long"
    },
    {
        "GPA":3.94,
        "A%":85,
        "B%":5,
        "C%":0,
        "D%":0,
        "F%":0,
        "Professor":"Chava, Sudheer"
    },
    {
        "GPA":3.85,
        "A%":87,
        "B%":8,
        "C%":4,
        "D%":0,
        "F%":0,
        "Professor":"Church, Bryan"
    },
    {
        "GPA":3.91,
        "A%":91,
        "B%":5,
        "C%":0,
        "D%":0,
        "F%":0,
        "Professor":"Clarke, Jonathan"
    },
    {
        "GPA":4.0,
        "A%":100,
        "B%":0,
        "C%":0,
        "D%":0,
        "F%":0,
        "Professor":"Comiskey, Eugene"
    },
    {
        "GPA":4.0,
        "A%":100,
        "B%":0,
        "C%":0,
        "D%":0,
        "F%":0,
        "Professor":"Connell, Howard"
    },
    {
        "GPA":4.0,
        "A%":100,
        "B%":0,
        "C%":0,
        "D%":0,
        "F%":0,
        "Professor":"Conti, Annamaria"
    },
    {
        "GPA":4.0,
        "A%":100,
        "B%":0,
        "C%":0,
        "D%":0,
        "F%":0,
        "Professor":"Cowan, Joel"
    },
    {
        "GPA":4.0,
        "A%":100,
        "B%":0,
        "C%":0,
        "D%":0,
        "F%":0,
        "Professor":"Daloisio, Anthony"
    },
    {
        "GPA":4.0,
        "A%":50,
        "B%":0,
        "C%":0,
        "D%":0,
        "F%":0,
        "Professor":"Danis, Andras"
    },
    {
        "GPA":4.0,
        "A%":100,
        "B%":0,
        "C%":0,
        "D%":0,
        "F%":0,
        "Professor":"Dass, Nishant"
    },
    {
        "GPA":3.83,
        "A%":83,
        "B%":17,
        "C%":0,
        "D%":0,
        "F%":0,
        "Professor":"Davis, Carolyn"
    },
    {
        "GPA":4.0,
        "A%":92,
        "B%":0,
        "C%":0,
        "D%":0,
        "F%":0,
        "Professor":"Dickson, Pat"
    },
    {
        "GPA":4.0,
        "A%":76,
        "B%":0,
        "C%":0,
        "D%":0,
        "F%":0,
        "Professor":"Dommer, Sara"
    },
    {
        "GPA":4.0,
        "A%":88,
        "B%":0,
        "C%":0,
        "D%":0,
        "F%":0,
        "Professor":"Ely, Kirsten"
    },
    {
        "GPA":4.0,
        "A%":88,
        "B%":0,
        "C%":0,
        "D%":0,
        "F%":0,
        "Professor":"Eun, Cheol"
    },
    {
        "GPA":4.0,
        "A%":100,
        "B%":0,
        "C%":0,
        "D%":0,
        "F%":0,
        "Professor":"Evans, Gail"
    },
    {
        "GPA":3.08,
        "A%":46,
        "B%":8,
        "C%":25,
        "D%":0,
        "F%":8,
        "Professor":"Fedor, Donald"
    },
    {
        "GPA":3.96,
        "A%":91,
        "B%":4,
        "C%":0,
        "D%":0,
        "F%":0,
        "Professor":"Ferguson, Mark"
    },
    {
        "GPA":3.78,
        "A%":83,
        "B%":15,
        "C%":0,
        "D%":0,
        "F%":2,
        "Professor":"Flury, Alan"
    },
    {
        "GPA":3.96,
        "A%":93,
        "B%":4,
        "C%":0,
        "D%":0,
        "F%":0,
        "Professor":"Forman, Christopher"
    },
    {
        "GPA":4.0,
        "A%":50,
        "B%":0,
        "C%":0,
        "D%":0,
        "F%":0,
        "Professor":"Fulmer, Ingrid"
    },
    {
        "GPA":3.91,
        "A%":96,
        "B%":0,
        "C%":4,
        "D%":0,
        "F%":0,
        "Professor":"Gaimon, Cheryl"
    },
    {
        "GPA":4.0,
        "A%":100,
        "B%":0,
        "C%":0,
        "D%":0,
        "F%":0,
        "Professor":"Gemmell, Robert"
    },
    {
        "GPA":4.0,
        "A%":100,
        "B%":0,
        "C%":0,
        "D%":0,
        "F%":0,
        "Professor":"Ghosh, Soumen"
    },
    {
        "GPA":3.92,
        "A%":73,
        "B%":8,
        "C%":0,
        "D%":0,
        "F%":0,
        "Professor":"Giuliano, Jonathan"
    },
    {
        "GPA":4.0,
        "A%":100,
        "B%":0,
        "C%":0,
        "D%":0,
        "F%":0,
        "Professor":"Goldsman, David"
    },
    {
        "GPA":4.0,
        "A%":100,
        "B%":0,
        "C%":0,
        "D%":0,
        "F%":0,
        "Professor":"Graham, Stuart"
    },
    {
        "GPA":3.0,
        "A%":50,
        "B%":0,
        "C%":50,
        "D%":0,
        "F%":0,
        "Professor":"Gu, Naiqing"
    },
    {
        "GPA":4.0,
        "A%":100,
        "B%":0,
        "C%":0,
        "D%":0,
        "F%":0,
        "Professor":"Hackett, Aaron"
    },
    {
        "GPA":4.0,
        "A%":79,
        "B%":0,
        "C%":0,
        "D%":0,
        "F%":0,
        "Professor":"Hales, Jeffrey"
    },
    {
        "GPA":4.0,
        "A%":100,
        "B%":0,
        "C%":0,
        "D%":0,
        "F%":0,
        "Professor":"Herndon, Benjamin"
    },
    {
        "GPA":4.0,
        "A%":78,
        "B%":0,
        "C%":0,
        "D%":0,
        "F%":0,
        "Professor":"Herold, David"
    },
    {
        "GPA":3.95,
        "A%":95,
        "B%":5,
        "C%":0,
        "D%":0,
        "F%":0,
        "Professor":"Higgins, Matthew"
    },
    {
        "GPA":4.0,
        "A%":100,
        "B%":0,
        "C%":0,
        "D%":0,
        "F%":0,
        "Professor":"Hodgson, Lara OConnor"
    },
    {
        "GPA":3.92,
        "A%":88,
        "B%":8,
        "C%":0,
        "D%":0,
        "F%":0,
        "Professor":"Hora, Manpreet"
    },
    {
        "GPA":4.0,
        "A%":100,
        "B%":0,
        "C%":0,
        "D%":0,
        "F%":0,
        "Professor":"Hu, Yu"
    },
    {
        "GPA":4.0,
        "A%":100,
        "B%":0,
        "C%":0,
        "D%":0,
        "F%":0,
        "Professor":"James, Lawrence"
    },
    {
        "GPA":4.0,
        "A%":48,
        "B%":0,
        "C%":0,
        "D%":0,
        "F%":0,
        "Professor":"Jayaraman, Narayanan"
    },
    {
        "GPA":3.94,
        "A%":94,
        "B%":6,
        "C%":0,
        "D%":0,
        "F%":0,
        "Professor":"Jayaraman, Sundaresan"
    },
    {
        "GPA":4.0,
        "A%":100,
        "B%":0,
        "C%":0,
        "D%":0,
        "F%":0,
        "Professor":"Jing, Xiaoqing"
    },
    {
        "GPA":2.0,
        "A%":0,
        "B%":0,
        "C%":100,
        "D%":0,
        "F%":0,
        "Professor":"Johnson, Tiffany"
    },
    {
        "GPA":4.0,
        "A%":100,
        "B%":0,
        "C%":0,
        "D%":0,
        "F%":0,
        "Professor":"Kalkanci, Basak"
    },
    {
        "GPA":3.98,
        "A%":89,
        "B%":2,
        "C%":0,
        "D%":0,
        "F%":0,
        "Professor":"Kavadias, Stylianos"
    },
    {
        "GPA":4.0,
        "A%":100,
        "B%":0,
        "C%":0,
        "D%":0,
        "F%":0,
        "Professor":"Kim, Soohun"
    },
    {
        "GPA":4.0,
        "A%":100,
        "B%":0,
        "C%":0,
        "D%":0,
        "F%":0,
        "Professor":"Kirkman, Bradley"
    },
    {
        "GPA":3.43,
        "A%":43,
        "B%":57,
        "C%":0,
        "D%":0,
        "F%":0,
        "Professor":"Kohli, Ajay"
    },
    {
        "GPA":4.0,
        "A%":100,
        "B%":0,
        "C%":0,
        "D%":0,
        "F%":0,
        "Professor":"Ku, David"
    },
    {
        "GPA":4.0,
        "A%":100,
        "B%":0,
        "C%":0,
        "D%":0,
        "F%":0,
        "Professor":"Kuang, Xi"
    },
    {
        "GPA":4.0,
        "A%":100,
        "B%":0,
        "C%":0,
        "D%":0,
        "F%":0,
        "Professor":"Kurre, Kathleen"
    },
    {
        "GPA":4.0,
        "A%":100,
        "B%":0,
        "C%":0,
        "D%":0,
        "F%":0,
        "Professor":"Lee, Jay"
    },
    {
        "GPA":4.0,
        "A%":96,
        "B%":0,
        "C%":0,
        "D%":0,
        "F%":0,
        "Professor":"Lee, Seo"
    },
    {
        "GPA":4.0,
        "A%":100,
        "B%":0,
        "C%":0,
        "D%":0,
        "F%":0,
        "Professor":"Levy, Ferdinand"
    },
    {
        "GPA":4.0,
        "A%":100,
        "B%":0,
        "C%":0,
        "D%":0,
        "F%":0,
        "Professor":"Liu, Dong"
    },
    {
        "GPA":4.0,
        "A%":100,
        "B%":0,
        "C%":0,
        "D%":0,
        "F%":0,
        "Professor":"Lowe, Michael"
    },
    {
        "GPA":4.0,
        "A%":90,
        "B%":0,
        "C%":0,
        "D%":0,
        "F%":0,
        "Professor":"Lurie, Nicholas"
    },
    {
        "GPA":3.94,
        "A%":94,
        "B%":6,
        "C%":0,
        "D%":0,
        "F%":0,
        "Professor":"Malhotra, Naresh"
    },
    {
        "GPA":3.67,
        "A%":83,
        "B%":0,
        "C%":17,
        "D%":0,
        "F%":0,
        "Professor":"Martins, Luis"
    },
    {
        "GPA":4.0,
        "A%":100,
        "B%":0,
        "C%":0,
        "D%":0,
        "F%":0,
        "Professor":"McIntyre, John"
    },
    {
        "GPA":3.92,
        "A%":92,
        "B%":8,
        "C%":0,
        "D%":0,
        "F%":0,
        "Professor":"Mitra, Sabyasachi"
    },
    {
        "GPA":4.0,
        "A%":100,
        "B%":0,
        "C%":0,
        "D%":0,
        "F%":0,
        "Professor":"Mulford Jr, Charles"
    },
    {
        "GPA":4.0,
        "A%":100,
        "B%":0,
        "C%":0,
        "D%":0,
        "F%":0,
        "Professor":"Mulford, Charles"
    },
    {
        "GPA":4.0,
        "A%":50,
        "B%":0,
        "C%":0,
        "D%":0,
        "F%":0,
        "Professor":"Murthy, Nagesh"
    },
    {
        "GPA":4.0,
        "A%":100,
        "B%":0,
        "C%":0,
        "D%":0,
        "F%":0,
        "Professor":"Myers, Robert"
    },
    {
        "GPA":4.0,
        "A%":100,
        "B%":0,
        "C%":0,
        "D%":0,
        "F%":0,
        "Professor":"Nanda, Vikram"
    },
    {
        "GPA":3.94,
        "A%":94,
        "B%":4,
        "C%":1,
        "D%":0,
        "F%":0,
        "Professor":"Narasimhan, Sridhar"
    },
    {
        "GPA":4.0,
        "A%":100,
        "B%":0,
        "C%":0,
        "D%":0,
        "F%":0,
        "Professor":"Nezafat, Mahdi"
    },
    {
        "GPA":3.93,
        "A%":93,
        "B%":7,
        "C%":0,
        "D%":0,
        "F%":0,
        "Professor":"Niculescu, Marius"
    },
    {
        "GPA":4.0,
        "A%":100,
        "B%":0,
        "C%":0,
        "D%":0,
        "F%":0,
        "Professor":"Oettl, Alexander"
    },
    {
        "GPA":4.0,
        "A%":100,
        "B%":0,
        "C%":0,
        "D%":0,
        "F%":0,
        "Professor":"Overby, Eric"
    },
    {
        "GPA":4.0,
        "A%":100,
        "B%":0,
        "C%":0,
        "D%":0,
        "F%":0,
        "Professor":"Oxman, Michael"
    },
    {
        "GPA":3.81,
        "A%":77,
        "B%":4,
        "C%":0,
        "D%":4,
        "F%":0,
        "Professor":"Parsons, Charles"
    },
    {
        "GPA":4.0,
        "A%":100,
        "B%":0,
        "C%":0,
        "D%":0,
        "F%":0,
        "Professor":"Pattabhiramaiah, Adithya"
    },
    {
        "GPA":4.0,
        "A%":100,
        "B%":0,
        "C%":0,
        "D%":0,
        "F%":0,
        "Professor":"Rahmani, Morvarid"
    },
    {
        "GPA":4.0,
        "A%":100,
        "B%":0,
        "C%":0,
        "D%":0,
        "F%":0,
        "Professor":"Ramachandran, Karthik"
    },
    {
        "GPA":4.0,
        "A%":100,
        "B%":0,
        "C%":0,
        "D%":0,
        "F%":0,
        "Professor":"Rodriguez Vila, Omar"
    },
    {
        "GPA":3.96,
        "A%":98,
        "B%":1,
        "C%":0,
        "D%":0,
        "F%":1,
        "Professor":"Rothaermel, Frank"
    },
    {
        "GPA":4.0,
        "A%":100,
        "B%":0,
        "C%":0,
        "D%":0,
        "F%":0,
        "Professor":"Rouse, William"
    },
    {
        "GPA":4.0,
        "A%":100,
        "B%":0,
        "C%":0,
        "D%":0,
        "F%":0,
        "Professor":"Rubinoff, Arnold"
    },
    {
        "GPA":4.0,
        "A%":100,
        "B%":0,
        "C%":0,
        "D%":0,
        "F%":0,
        "Professor":"Sauermann, Henry"
    },
    {
        "GPA":4.0,
        "A%":98,
        "B%":0,
        "C%":0,
        "D%":0,
        "F%":0,
        "Professor":"Schneider, Arnold"
    },
    {
        "GPA":4.0,
        "A%":100,
        "B%":0,
        "C%":0,
        "D%":0,
        "F%":0,
        "Professor":"Shallenberger, David"
    },
    {
        "GPA":3.89,
        "A%":83,
        "B%":11,
        "C%":0,
        "D%":0,
        "F%":0,
        "Professor":"Shalley, Christina"
    },
    {
        "GPA":4.0,
        "A%":100,
        "B%":0,
        "C%":0,
        "D%":0,
        "F%":0,
        "Professor":"Singh, Manpreet"
    },
    {
        "GPA":4.0,
        "A%":100,
        "B%":0,
        "C%":0,
        "D%":0,
        "F%":0,
        "Professor":"Singhal, Vinod"
    },
    {
        "GPA":4.0,
        "A%":96,
        "B%":0,
        "C%":0,
        "D%":0,
        "F%":0,
        "Professor":"Slaughter, Sandra"
    },
    {
        "GPA":4.0,
        "A%":100,
        "B%":0,
        "C%":0,
        "D%":0,
        "F%":0,
        "Professor":"Sluss, David"
    },
    {
        "GPA":4.0,
        "A%":100,
        "B%":0,
        "C%":0,
        "D%":0,
        "F%":0,
        "Professor":"Smith, Michael"
    },
    {
        "GPA":4.0,
        "A%":89,
        "B%":0,
        "C%":0,
        "D%":0,
        "F%":0,
        "Professor":"Soni, Samit"
    },
    {
        "GPA":4.0,
        "A%":100,
        "B%":0,
        "C%":0,
        "D%":0,
        "F%":0,
        "Professor":"Subramanian, Ajay"
    },
    {
        "GPA":4.0,
        "A%":81,
        "B%":0,
        "C%":0,
        "D%":0,
        "F%":0,
        "Professor":"Subramanian, Ravi"
    },
    {
        "GPA":4.0,
        "A%":100,
        "B%":0,
        "C%":0,
        "D%":0,
        "F%":0,
        "Professor":"Sutherland, David"
    },
    {
        "GPA":4.0,
        "A%":100,
        "B%":0,
        "C%":0,
        "D%":0,
        "F%":0,
        "Professor":"Swider, Brian"
    },
    {
        "GPA":4.0,
        "A%":100,
        "B%":0,
        "C%":0,
        "D%":0,
        "F%":0,
        "Professor":"Swire, Peter"
    },
    {
        "GPA":4.0,
        "A%":99,
        "B%":0,
        "C%":0,
        "D%":0,
        "F%":0,
        "Professor":"Teach, Richard"
    },
    {
        "GPA":4.0,
        "A%":83,
        "B%":0,
        "C%":0,
        "D%":0,
        "F%":0,
        "Professor":"Thompson, Peter"
    },
    {
        "GPA":4.0,
        "A%":100,
        "B%":0,
        "C%":0,
        "D%":0,
        "F%":0,
        "Professor":"Thursby, Jerry"
    },
    {
        "GPA":3.93,
        "A%":83,
        "B%":7,
        "C%":0,
        "D%":0,
        "F%":0,
        "Professor":"Thursby, Marie"
    },
    {
        "GPA":4.0,
        "A%":100,
        "B%":0,
        "C%":0,
        "D%":0,
        "F%":0,
        "Professor":"Todd, William"
    },
    {
        "GPA":4.0,
        "A%":98,
        "B%":0,
        "C%":0,
        "D%":0,
        "F%":0,
        "Professor":"Toktay-Tsiotras, Latife"
    },
    {
        "GPA":4.0,
        "A%":99,
        "B%":0,
        "C%":0,
        "D%":0,
        "F%":0,
        "Professor":"Turner, Deborah"
    },
    {
        "GPA":4.0,
        "A%":100,
        "B%":0,
        "C%":0,
        "D%":0,
        "F%":0,
        "Professor":"Ulgado, Francis"
    },
    {
        "GPA":3.94,
        "A%":84,
        "B%":6,
        "C%":0,
        "D%":0,
        "F%":0,
        "Professor":"Van Ittersum, Koert"
    },
    {
        "GPA":4.0,
        "A%":100,
        "B%":0,
        "C%":0,
        "D%":0,
        "F%":0,
        "Professor":"Vantine, Peter"
    },
    {
        "GPA":4.0,
        "A%":100,
        "B%":0,
        "C%":0,
        "D%":0,
        "F%":0,
        "Professor":"Voigt, Nicholas"
    },
    {
        "GPA":4.0,
        "A%":100,
        "B%":0,
        "C%":0,
        "D%":0,
        "F%":0,
        "Professor":"Wang, Qinghai"
    },
    {
        "GPA":4.0,
        "A%":100,
        "B%":0,
        "C%":0,
        "D%":0,
        "F%":0,
        "Professor":"Weagley, Daniel"
    },
    {
        "GPA":4.0,
        "A%":100,
        "B%":0,
        "C%":0,
        "D%":0,
        "F%":0,
        "Professor":"Wong, Nancy"
    },
    {
        "GPA":4.0,
        "A%":77,
        "B%":0,
        "C%":0,
        "D%":0,
        "F%":0,
        "Professor":"Wright, Beverly"
    },
    {
        "GPA":4.0,
        "A%":100,
        "B%":0,
        "C%":0,
        "D%":0,
        "F%":0,
        "Professor":"Wu, Dongjun"
    },
    {
        "GPA":4.0,
        "A%":98,
        "B%":0,
        "C%":0,
        "D%":0,
        "F%":0,
        "Professor":"Zhang, Han"
    }
]