[
    {
        "GPA":3.35,
        "A%":59.0,
        "B%":21.0,
        "C%":9.0,
        "D%":3.0,
        "F%":3.0,
        "Course":"All"
    },
    {
        "GPA":2.8680645161,
        "A%":33.1935483871,
        "B%":31.8064516129,
        "C%":15.8387096774,
        "D%":6.3870967742,
        "F%":2.9677419355,
        "Course":"CS 1312"
    },
    {
        "GPA":2.7233333333,
        "A%":28.6666666667,
        "B%":36.0,
        "C%":17.0,
        "D%":3.3333333333,
        "F%":10.6666666667,
        "Course":"CS 1321"
    },
    {
        "GPA":2.5342857143,
        "A%":28.2857142857,
        "B%":24.4761904762,
        "C%":21.619047619,
        "D%":9.8571428571,
        "F%":10.7619047619,
        "Course":"CS 1322"
    },
    {
        "GPA":2.4154545455,
        "A%":23.8181818182,
        "B%":28.5606060606,
        "C%":17.5151515152,
        "D%":7.0606060606,
        "F%":7.2121212121,
        "Course":"CS 1331"
    },
    {
        "GPA":3.6,
        "A%":60.0,
        "B%":40.0,
        "C%":0.0,
        "D%":0.0,
        "F%":0.0,
        "Course":"CS 2699"
    },
    {
        "GPA":4.0,
        "A%":100.0,
        "B%":0.0,
        "C%":0.0,
        "D%":0.0,
        "F%":0.0,
        "Course":"CS 3901"
    },
    {
        "GPA":2.42,
        "A%":13.6666666667,
        "B%":37.3333333333,
        "C%":19.6666666667,
        "D%":13.0,
        "F%":7.3333333333,
        "Course":"CS 4460"
    },
    {
        "GPA":3.9411764706,
        "A%":94.1176470588,
        "B%":5.8823529412,
        "C%":0.0,
        "D%":0.0,
        "F%":0.0,
        "Course":"CS 4699"
    },
    {
        "GPA":2.84,
        "A%":25.0,
        "B%":32.5,
        "C%":33.5,
        "D%":3.5,
        "F%":0.0,
        "Course":"CS 4750"
    },
    {
        "GPA":2.0,
        "A%":42.0,
        "B%":0.0,
        "C%":0.0,
        "D%":0.0,
        "F%":0.0,
        "Course":"CS 4801"
    },
    {
        "GPA":4.0,
        "A%":100.0,
        "B%":0.0,
        "C%":0.0,
        "D%":0.0,
        "F%":0.0,
        "Course":"CS 4901"
    },
    {
        "GPA":3.7881818182,
        "A%":78.8181818182,
        "B%":21.1818181818,
        "C%":0.0,
        "D%":0.0,
        "F%":0.0,
        "Course":"CS 4903"
    },
    {
        "GPA":3.75,
        "A%":75.0,
        "B%":25.0,
        "C%":0.0,
        "D%":0.0,
        "F%":0.0,
        "Course":"CS 4980"
    },
    {
        "GPA":3.93,
        "A%":88.0,
        "B%":6.0,
        "C%":0.0,
        "D%":0.0,
        "F%":0.0,
        "Course":"CS 6452"
    },
    {
        "GPA":3.29,
        "A%":38.0,
        "B%":44.0,
        "C%":7.0,
        "D%":2.0,
        "F%":0.0,
        "Course":"CS 6750"
    },
    {
        "GPA":3.7647058824,
        "A%":75.4705882353,
        "B%":22.5294117647,
        "C%":0.0,
        "D%":0.0,
        "F%":0.0,
        "Course":"CS 6998"
    },
    {
        "GPA":3.7142857143,
        "A%":92.8571428571,
        "B%":0.0,
        "C%":0.0,
        "D%":0.0,
        "F%":7.1428571429,
        "Course":"CS 6999"
    },
    {
        "GPA":3.4555,
        "A%":53.6,
        "B%":31.35,
        "C%":6.15,
        "D%":1.4,
        "F%":0.65,
        "Course":"CS 7450"
    },
    {
        "GPA":0.0,
        "A%":0.0,
        "B%":0.0,
        "C%":0.0,
        "D%":0.0,
        "F%":0.0,
        "Course":"CS 8001"
    },
    {
        "GPA":3.7665,
        "A%":87.1,
        "B%":2.5,
        "C%":10.4,
        "D%":0.0,
        "F%":0.0,
        "Course":"CS 8902"
    },
    {
        "GPA":3.9057407407,
        "A%":86.5925925926,
        "B%":7.2962962963,
        "C%":0.9259259259,
        "D%":0.0,
        "F%":0.0,
        "Course":"CS 8903"
    },
    {
        "GPA":0.0,
        "A%":0.0,
        "B%":0.0,
        "C%":0.0,
        "D%":0.0,
        "F%":0.0,
        "Course":"ISYE 4801"
    },
    {
        "GPA":2.895,
        "A%":23.5,
        "B%":31.0,
        "C%":14.5,
        "D%":14.5,
        "F%":0.0,
        "Course":"PSYC 4750"
    },
    {
        "GPA":3.2366666667,
        "A%":37.0,
        "B%":49.6666666667,
        "C%":13.3333333333,
        "D%":0.0,
        "F%":0.0,
        "Course":"PSYC 6750"
    }
]