[
    {
        "GPA":3.81,
        "A%":83,
        "B%":11,
        "C%":4,
        "D%":0,
        "F%":0,
        "Professor":"All"
    },
    {
        "GPA":3.78,
        "A%":84,
        "B%":9,
        "C%":6,
        "D%":0,
        "F%":0,
        "Professor":"Al-Haddad, Tristan"
    },
    {
        "GPA":3.0,
        "A%":50,
        "B%":0,
        "C%":50,
        "D%":0,
        "F%":0,
        "Professor":"Alkanoglu, Volkan"
    },
    {
        "GPA":4.0,
        "A%":100,
        "B%":0,
        "C%":0,
        "D%":0,
        "F%":0,
        "Professor":"Andreotti, Libero"
    },
    {
        "GPA":3.98,
        "A%":97,
        "B%":2,
        "C%":0,
        "D%":0,
        "F%":0,
        "Professor":"Augenbroe, Godfried"
    },
    {
        "GPA":4.0,
        "A%":100,
        "B%":0,
        "C%":0,
        "D%":0,
        "F%":0,
        "Professor":"Baerlecken, Daniel"
    },
    {
        "GPA":3.8,
        "A%":80,
        "B%":20,
        "C%":0,
        "D%":0,
        "F%":0,
        "Professor":"Bafna, Sonit"
    },
    {
        "GPA":4.0,
        "A%":100,
        "B%":0,
        "C%":0,
        "D%":0,
        "F%":0,
        "Professor":"Balfour, Alan"
    },
    {
        "GPA":4.0,
        "A%":100,
        "B%":0,
        "C%":0,
        "D%":0,
        "F%":0,
        "Professor":"Bonnamour-Lloyd, Dominique"
    },
    {
        "GPA":3.2,
        "A%":53,
        "B%":13,
        "C%":33,
        "D%":0,
        "F%":0,
        "Professor":"Brown, Jason"
    },
    {
        "GPA":4.0,
        "A%":100,
        "B%":0,
        "C%":0,
        "D%":0,
        "F%":0,
        "Professor":"Craig, Robert"
    },
    {
        "GPA":3.47,
        "A%":48,
        "B%":50,
        "C%":2,
        "D%":0,
        "F%":0,
        "Professor":"Dagenhart, Richard"
    },
    {
        "GPA":3.39,
        "A%":50,
        "B%":39,
        "C%":11,
        "D%":0,
        "F%":0,
        "Professor":"Dessi-Olive, Jonathan"
    },
    {
        "GPA":4.0,
        "A%":100,
        "B%":0,
        "C%":0,
        "D%":0,
        "F%":0,
        "Professor":"Do, Yi-Luen"
    },
    {
        "GPA":4.0,
        "A%":100,
        "B%":0,
        "C%":0,
        "D%":0,
        "F%":0,
        "Professor":"Dobbins, Michael"
    },
    {
        "GPA":3.65,
        "A%":78,
        "B%":10,
        "C%":13,
        "D%":0,
        "F%":0,
        "Professor":"Dreger, Garvin"
    },
    {
        "GPA":3.87,
        "A%":87,
        "B%":13,
        "C%":0,
        "D%":0,
        "F%":0,
        "Professor":"Dunham-Jones, Ellen"
    },
    {
        "GPA":4.0,
        "A%":100,
        "B%":0,
        "C%":0,
        "D%":0,
        "F%":0,
        "Professor":"Dusseault, Ruth"
    },
    {
        "GPA":4.0,
        "A%":100,
        "B%":0,
        "C%":0,
        "D%":0,
        "F%":0,
        "Professor":"Dye, Wanda"
    },
    {
        "GPA":3.97,
        "A%":97,
        "B%":3,
        "C%":0,
        "D%":0,
        "F%":0,
        "Professor":"Eastman, Charles"
    },
    {
        "GPA":3.98,
        "A%":98,
        "B%":2,
        "C%":0,
        "D%":0,
        "F%":0,
        "Professor":"Economou, Athanassios"
    },
    {
        "GPA":4.0,
        "A%":100,
        "B%":0,
        "C%":0,
        "D%":0,
        "F%":0,
        "Professor":"Farrow, Robert"
    },
    {
        "GPA":4.0,
        "A%":100,
        "B%":0,
        "C%":0,
        "D%":0,
        "F%":0,
        "Professor":"Flowers, Benjamin"
    },
    {
        "GPA":4.0,
        "A%":100,
        "B%":0,
        "C%":0,
        "D%":0,
        "F%":0,
        "Professor":"Gamble, Michael"
    },
    {
        "GPA":3.94,
        "A%":89,
        "B%":6,
        "C%":0,
        "D%":0,
        "F%":0,
        "Professor":"Gentry, T"
    },
    {
        "GPA":3.5,
        "A%":50,
        "B%":17,
        "C%":0,
        "D%":0,
        "F%":0,
        "Professor":"Gentry, Thomas"
    },
    {
        "GPA":4.0,
        "A%":100,
        "B%":0,
        "C%":0,
        "D%":0,
        "F%":0,
        "Professor":"Gravel, Ryan"
    },
    {
        "GPA":4.0,
        "A%":100,
        "B%":0,
        "C%":0,
        "D%":0,
        "F%":0,
        "Professor":"Green, David"
    },
    {
        "GPA":4.0,
        "A%":100,
        "B%":0,
        "C%":0,
        "D%":0,
        "F%":0,
        "Professor":"Haymaker, John"
    },
    {
        "GPA":4.0,
        "A%":100,
        "B%":0,
        "C%":0,
        "D%":0,
        "F%":0,
        "Professor":"He, Weiling"
    },
    {
        "GPA":4.0,
        "A%":67,
        "B%":0,
        "C%":0,
        "D%":0,
        "F%":0,
        "Professor":"Hickman, Lauren"
    },
    {
        "GPA":3.46,
        "A%":46,
        "B%":54,
        "C%":0,
        "D%":0,
        "F%":0,
        "Professor":"Hollengreen, Laura"
    },
    {
        "GPA":4.0,
        "A%":100,
        "B%":0,
        "C%":0,
        "D%":0,
        "F%":0,
        "Professor":"Howard, Herman"
    },
    {
        "GPA":4.0,
        "A%":100,
        "B%":0,
        "C%":0,
        "D%":0,
        "F%":0,
        "Professor":"Jarrett, Christopher"
    },
    {
        "GPA":3.33,
        "A%":67,
        "B%":0,
        "C%":33,
        "D%":0,
        "F%":0,
        "Professor":"Johnston, George"
    },
    {
        "GPA":3.67,
        "A%":67,
        "B%":33,
        "C%":0,
        "D%":0,
        "F%":0,
        "Professor":"Kangari, Roozbeh"
    },
    {
        "GPA":3.75,
        "A%":42,
        "B%":17,
        "C%":0,
        "D%":0,
        "F%":0,
        "Professor":"Kaseman, Keith"
    },
    {
        "GPA":4.0,
        "A%":100,
        "B%":0,
        "C%":0,
        "D%":0,
        "F%":0,
        "Professor":"Khan, Sabir"
    },
    {
        "GPA":4.0,
        "A%":100,
        "B%":0,
        "C%":0,
        "D%":0,
        "F%":0,
        "Professor":"Kim, Julie"
    },
    {
        "GPA":4.0,
        "A%":100,
        "B%":0,
        "C%":0,
        "D%":0,
        "F%":0,
        "Professor":"Leblanc, W"
    },
    {
        "GPA":3.68,
        "A%":77,
        "B%":18,
        "C%":0,
        "D%":5,
        "F%":0,
        "Professor":"LeBlanc, William"
    },
    {
        "GPA":4.0,
        "A%":100,
        "B%":0,
        "C%":0,
        "D%":0,
        "F%":0,
        "Professor":"McJunkin, Mark"
    },
    {
        "GPA":4.0,
        "A%":100,
        "B%":0,
        "C%":0,
        "D%":0,
        "F%":0,
        "Professor":"Mesa Molina, Debora"
    },
    {
        "GPA":3.0,
        "A%":0,
        "B%":100,
        "C%":0,
        "D%":0,
        "F%":0,
        "Professor":"Messadi, Tahar"
    },
    {
        "GPA":4.0,
        "A%":100,
        "B%":0,
        "C%":0,
        "D%":0,
        "F%":0,
        "Professor":"Oberle, Rita"
    },
    {
        "GPA":4.0,
        "A%":100,
        "B%":0,
        "C%":0,
        "D%":0,
        "F%":0,
        "Professor":"Pearsall, Frederick"
    },
    {
        "GPA":3.86,
        "A%":79,
        "B%":14,
        "C%":0,
        "D%":0,
        "F%":0,
        "Professor":"Peponis, John"
    },
    {
        "GPA":4.0,
        "A%":100,
        "B%":0,
        "C%":0,
        "D%":0,
        "F%":0,
        "Professor":"Porter, Richard"
    },
    {
        "GPA":3.0,
        "A%":0,
        "B%":100,
        "C%":0,
        "D%":0,
        "F%":0,
        "Professor":"Pyburn, Jack"
    },
    {
        "GPA":2.8,
        "A%":33,
        "B%":33,
        "C%":0,
        "D%":0,
        "F%":17,
        "Professor":"Rakha, Tarek"
    },
    {
        "GPA":4.0,
        "A%":100,
        "B%":0,
        "C%":0,
        "D%":0,
        "F%":0,
        "Professor":"Riether, Gernot"
    },
    {
        "GPA":4.0,
        "A%":100,
        "B%":0,
        "C%":0,
        "D%":0,
        "F%":0,
        "Professor":"Romm, Stuart"
    },
    {
        "GPA":4.0,
        "A%":100,
        "B%":0,
        "C%":0,
        "D%":0,
        "F%":0,
        "Professor":"Rudolph, Charles"
    },
    {
        "GPA":4.0,
        "A%":100,
        "B%":0,
        "C%":0,
        "D%":0,
        "F%":0,
        "Professor":"Sadri, Saeid"
    },
    {
        "GPA":3.5,
        "A%":50,
        "B%":50,
        "C%":0,
        "D%":0,
        "F%":0,
        "Professor":"Sanford, Jon"
    },
    {
        "GPA":4.0,
        "A%":100,
        "B%":0,
        "C%":0,
        "D%":0,
        "F%":0,
        "Professor":"Sharp, Leslie"
    },
    {
        "GPA":4.0,
        "A%":92,
        "B%":0,
        "C%":0,
        "D%":0,
        "F%":0,
        "Professor":"Shelden, Dennis"
    },
    {
        "GPA":4.0,
        "A%":100,
        "B%":0,
        "C%":0,
        "D%":0,
        "F%":0,
        "Professor":"Simmons, Marc"
    },
    {
        "GPA":4.0,
        "A%":100,
        "B%":0,
        "C%":0,
        "D%":0,
        "F%":0,
        "Professor":"Spuijbroek, Lars"
    },
    {
        "GPA":4.0,
        "A%":100,
        "B%":0,
        "C%":0,
        "D%":0,
        "F%":0,
        "Professor":"Swarts, Matthew"
    },
    {
        "GPA":4.0,
        "A%":100,
        "B%":0,
        "C%":0,
        "D%":0,
        "F%":0,
        "Professor":"Wang, Wei"
    },
    {
        "GPA":3.0,
        "A%":0,
        "B%":100,
        "C%":0,
        "D%":0,
        "F%":0,
        "Professor":"Weidner, Maureen"
    },
    {
        "GPA":4.0,
        "A%":100,
        "B%":0,
        "C%":0,
        "D%":0,
        "F%":0,
        "Professor":"Yang, Perry"
    },
    {
        "GPA":3.87,
        "A%":90,
        "B%":8,
        "C%":3,
        "D%":0,
        "F%":0,
        "Professor":"Zimring, Craig"
    }
]