[
    {
        "GPA":3.42,
        "A%":46,
        "B%":25,
        "C%":7,
        "D%":1,
        "F%":1,
        "Professor":"All"
    },
    {
        "GPA":3.63,
        "A%":64,
        "B%":22,
        "C%":3,
        "D%":1,
        "F%":1,
        "Professor":"Conte, Thomas"
    },
    {
        "GPA":3.69,
        "A%":41,
        "B%":18,
        "C%":0,
        "D%":0,
        "F%":0,
        "Professor":"Esmaeilzadeh, Hadi"
    },
    {
        "GPA":3.34,
        "A%":47,
        "B%":32,
        "C%":14,
        "D%":0,
        "F%":1,
        "Professor":"Kim, Hyesoon"
    },
    {
        "GPA":4.0,
        "A%":50,
        "B%":0,
        "C%":0,
        "D%":0,
        "F%":0,
        "Professor":"Kim, Jongman"
    },
    {
        "GPA":3.6,
        "A%":80,
        "B%":0,
        "C%":20,
        "D%":0,
        "F%":0,
        "Professor":"Krishna, Tushar"
    },
    {
        "GPA":3.2,
        "A%":42,
        "B%":43,
        "C%":4,
        "D%":0,
        "F%":7,
        "Professor":"Loh, Gabriel"
    },
    {
        "GPA":3.63,
        "A%":67,
        "B%":25,
        "C%":5,
        "D%":0,
        "F%":0,
        "Professor":"Mackenzie, Kenneth"
    },
    {
        "GPA":3.31,
        "A%":45,
        "B%":39,
        "C%":9,
        "D%":0,
        "F%":2,
        "Professor":"Niemier, Michael"
    },
    {
        "GPA":3.75,
        "A%":50,
        "B%":17,
        "C%":0,
        "D%":0,
        "F%":0,
        "Professor":"Park, Sunjae"
    },
    {
        "GPA":3.11,
        "A%":34,
        "B%":25,
        "C%":9,
        "D%":3,
        "F%":3,
        "Professor":"Prvulovic, Milos"
    },
    {
        "GPA":3.31,
        "A%":49,
        "B%":27,
        "C%":21,
        "D%":0,
        "F%":0,
        "Professor":"Qureshi, Moinuddin"
    },
    {
        "GPA":3.58,
        "A%":30,
        "B%":22,
        "C%":0,
        "D%":0,
        "F%":0,
        "Professor":"Railing, Brian"
    }
]