[
    {
        "GPA":3.96,
        "A%":97,
        "B%":1,
        "C%":2,
        "D%":0,
        "F%":0,
        "Professor":"All"
    },
    {
        "GPA":4.0,
        "A%":100,
        "B%":0,
        "C%":0,
        "D%":0,
        "F%":0,
        "Professor":"Bergin, Michael"
    },
    {
        "GPA":4.0,
        "A%":100,
        "B%":0,
        "C%":0,
        "D%":0,
        "F%":0,
        "Professor":"Chen, Yongsheng"
    },
    {
        "GPA":4.0,
        "A%":100,
        "B%":0,
        "C%":0,
        "D%":0,
        "F%":0,
        "Professor":"Desroches, Reginald"
    },
    {
        "GPA":4.0,
        "A%":100,
        "B%":0,
        "C%":0,
        "D%":0,
        "F%":0,
        "Professor":"Emkin, Leroy"
    },
    {
        "GPA":3.88,
        "A%":88,
        "B%":13,
        "C%":0,
        "D%":0,
        "F%":0,
        "Professor":"Germanovich, Leonid"
    },
    {
        "GPA":4.0,
        "A%":100,
        "B%":0,
        "C%":0,
        "D%":0,
        "F%":0,
        "Professor":"Haj-Ali, Rami"
    },
    {
        "GPA":4.0,
        "A%":100,
        "B%":0,
        "C%":0,
        "D%":0,
        "F%":0,
        "Professor":"Huang, Ching-Hua"
    },
    {
        "GPA":4.0,
        "A%":100,
        "B%":0,
        "C%":0,
        "D%":0,
        "F%":0,
        "Professor":"Jacobs, Laurence"
    },
    {
        "GPA":4.0,
        "A%":100,
        "B%":0,
        "C%":0,
        "D%":0,
        "F%":0,
        "Professor":"Kahn, Lawrence"
    },
    {
        "GPA":4.0,
        "A%":100,
        "B%":0,
        "C%":0,
        "D%":0,
        "F%":0,
        "Professor":"Kurtis, Kimberly"
    },
    {
        "GPA":3.0,
        "A%":50,
        "B%":0,
        "C%":50,
        "D%":0,
        "F%":0,
        "Professor":"Loeffler, Frank"
    },
    {
        "GPA":4.0,
        "A%":100,
        "B%":0,
        "C%":0,
        "D%":0,
        "F%":0,
        "Professor":"Pennell, Kurt"
    },
    {
        "GPA":4.0,
        "A%":100,
        "B%":0,
        "C%":0,
        "D%":0,
        "F%":0,
        "Professor":"Puzrin, Alexander"
    },
    {
        "GPA":4.0,
        "A%":100,
        "B%":0,
        "C%":0,
        "D%":0,
        "F%":0,
        "Professor":"Rix, Glenn"
    },
    {
        "GPA":4.0,
        "A%":100,
        "B%":0,
        "C%":0,
        "D%":0,
        "F%":0,
        "Professor":"Russell, Armistead"
    },
    {
        "GPA":4.0,
        "A%":100,
        "B%":0,
        "C%":0,
        "D%":0,
        "F%":0,
        "Professor":"Santamarina, Juan"
    },
    {
        "GPA":4.0,
        "A%":100,
        "B%":0,
        "C%":0,
        "D%":0,
        "F%":0,
        "Professor":"Spain, Jim"
    },
    {
        "GPA":4.0,
        "A%":100,
        "B%":0,
        "C%":0,
        "D%":0,
        "F%":0,
        "Professor":"Stieglitz, Marc"
    },
    {
        "GPA":4.0,
        "A%":100,
        "B%":0,
        "C%":0,
        "D%":0,
        "F%":0,
        "Professor":"Sturm, Terry"
    },
    {
        "GPA":4.0,
        "A%":100,
        "B%":0,
        "C%":0,
        "D%":0,
        "F%":0,
        "Professor":"Tsai, Yi-Chang"
    },
    {
        "GPA":4.0,
        "A%":100,
        "B%":0,
        "C%":0,
        "D%":0,
        "F%":0,
        "Professor":"Wang, Jingfeng"
    },
    {
        "GPA":4.0,
        "A%":100,
        "B%":0,
        "C%":0,
        "D%":0,
        "F%":0,
        "Professor":"Webster, Donald"
    },
    {
        "GPA":4.0,
        "A%":100,
        "B%":0,
        "C%":0,
        "D%":0,
        "F%":0,
        "Professor":"Zureick, Abdulhamid"
    }
]