[
    {
        "GPA":3.58,
        "A%":69,
        "B%":20,
        "C%":11,
        "D%":0,
        "F%":0,
        "Professor":"All"
    },
    {
        "GPA":3.25,
        "A%":25,
        "B%":75,
        "C%":0,
        "D%":0,
        "F%":0,
        "Professor":"Bost, Lewis"
    },
    {
        "GPA":3.56,
        "A%":70,
        "B%":15,
        "C%":14,
        "D%":0,
        "F%":0,
        "Professor":"Rains, James"
    },
    {
        "GPA":4.0,
        "A%":100,
        "B%":0,
        "C%":0,
        "D%":0,
        "F%":0,
        "Professor":"Stubbs, James"
    }
]