[
    {
        "GPA":3.73,
        "A%":73,
        "B%":17,
        "C%":2,
        "D%":1,
        "F%":0,
        "Professor":"All"
    },
    {
        "GPA":3.74,
        "A%":71,
        "B%":19,
        "C%":3,
        "D%":0,
        "F%":0,
        "Professor":"Augenbroe, Godfried"
    },
    {
        "GPA":4.0,
        "A%":100,
        "B%":0,
        "C%":0,
        "D%":0,
        "F%":0,
        "Professor":"Butler III, James"
    },
    {
        "GPA":3.75,
        "A%":92,
        "B%":0,
        "C%":0,
        "D%":9,
        "F%":0,
        "Professor":"Choudhary, Ruchi"
    },
    {
        "GPA":3.5,
        "A%":50,
        "B%":50,
        "C%":0,
        "D%":0,
        "F%":0,
        "Professor":"Diana, Carla"
    },
    {
        "GPA":4.0,
        "A%":94,
        "B%":0,
        "C%":0,
        "D%":0,
        "F%":0,
        "Professor":"Do, Yi-Luen"
    },
    {
        "GPA":3.84,
        "A%":74,
        "B%":15,
        "C%":0,
        "D%":0,
        "F%":0,
        "Professor":"Eastman, Charles"
    },
    {
        "GPA":3.56,
        "A%":57,
        "B%":44,
        "C%":0,
        "D%":0,
        "F%":0,
        "Professor":"Gentry, T"
    },
    {
        "GPA":3.58,
        "A%":73,
        "B%":13,
        "C%":0,
        "D%":7,
        "F%":0,
        "Professor":"Harp, Alan"
    },
    {
        "GPA":4.0,
        "A%":100,
        "B%":0,
        "C%":0,
        "D%":0,
        "F%":0,
        "Professor":"Lee, Ghang"
    },
    {
        "GPA":3.0,
        "A%":25,
        "B%":50,
        "C%":25,
        "D%":0,
        "F%":0,
        "Professor":"Mullick, Abir"
    },
    {
        "GPA":4.0,
        "A%":100,
        "B%":0,
        "C%":0,
        "D%":0,
        "F%":0,
        "Professor":"Oberle, Rita"
    },
    {
        "GPA":3.5,
        "A%":50,
        "B%":50,
        "C%":0,
        "D%":0,
        "F%":0,
        "Professor":"Shaw, Jonathan"
    },
    {
        "GPA":3.94,
        "A%":95,
        "B%":6,
        "C%":0,
        "D%":0,
        "F%":0,
        "Professor":"Thomas-Mobley, Linda"
    },
    {
        "GPA":4.0,
        "A%":75,
        "B%":0,
        "C%":0,
        "D%":0,
        "F%":0,
        "Professor":"Winegarden, Claudia"
    },
    {
        "GPA":2.67,
        "A%":40,
        "B%":0,
        "C%":0,
        "D%":0,
        "F%":20,
        "Professor":"Zimring, Craig"
    }
]