[
    {
        "GPA":3.77,
        "A%":84,
        "B%":11,
        "C%":3,
        "D%":0,
        "F%":2,
        "Professor":"All"
    },
    {
        "GPA":3.69,
        "A%":80,
        "B%":16,
        "C%":0,
        "D%":0,
        "F%":4,
        "Professor":"Augenbroe, Godfried"
    },
    {
        "GPA":4.0,
        "A%":100,
        "B%":0,
        "C%":0,
        "D%":0,
        "F%":0,
        "Professor":"Brown, Jason"
    },
    {
        "GPA":4.0,
        "A%":100,
        "B%":0,
        "C%":0,
        "D%":0,
        "F%":0,
        "Professor":"Budd, James"
    },
    {
        "GPA":3.33,
        "A%":67,
        "B%":0,
        "C%":33,
        "D%":0,
        "F%":0,
        "Professor":"Choudhary, Ruchi"
    },
    {
        "GPA":3.95,
        "A%":95,
        "B%":5,
        "C%":0,
        "D%":0,
        "F%":0,
        "Professor":"Do, Yi-Luen"
    },
    {
        "GPA":4.0,
        "A%":100,
        "B%":0,
        "C%":0,
        "D%":0,
        "F%":0,
        "Professor":"Dobbins, Michael"
    },
    {
        "GPA":3.89,
        "A%":93,
        "B%":2,
        "C%":5,
        "D%":0,
        "F%":0,
        "Professor":"Eastman, Charles"
    },
    {
        "GPA":4.0,
        "A%":100,
        "B%":0,
        "C%":0,
        "D%":0,
        "F%":0,
        "Professor":"Faust, Nickolas"
    },
    {
        "GPA":3.94,
        "A%":94,
        "B%":6,
        "C%":0,
        "D%":0,
        "F%":0,
        "Professor":"Gentry, T"
    },
    {
        "GPA":3.84,
        "A%":83,
        "B%":16,
        "C%":0,
        "D%":0,
        "F%":0,
        "Professor":"Justice, Lorraine"
    },
    {
        "GPA":4.0,
        "A%":100,
        "B%":0,
        "C%":0,
        "D%":0,
        "F%":0,
        "Professor":"Kangari, Roozbeh"
    },
    {
        "GPA":3.89,
        "A%":89,
        "B%":11,
        "C%":0,
        "D%":0,
        "F%":0,
        "Professor":"Koncelik, Joseph"
    },
    {
        "GPA":4.0,
        "A%":100,
        "B%":0,
        "C%":0,
        "D%":0,
        "F%":0,
        "Professor":"Medina, Joyce"
    },
    {
        "GPA":3.88,
        "A%":88,
        "B%":13,
        "C%":0,
        "D%":0,
        "F%":0,
        "Professor":"Messadi, Tahar"
    },
    {
        "GPA":3.25,
        "A%":25,
        "B%":75,
        "C%":0,
        "D%":0,
        "F%":0,
        "Professor":"Purdy, Timothy"
    },
    {
        "GPA":4.0,
        "A%":100,
        "B%":0,
        "C%":0,
        "D%":0,
        "F%":0,
        "Professor":"Reeder, Kevin"
    },
    {
        "GPA":2.0,
        "A%":0,
        "B%":0,
        "C%":100,
        "D%":0,
        "F%":0,
        "Professor":"Steinemann, Anne"
    }
]