[
    {
        "GPA":4.0,
        "A%":100,
        "B%":0,
        "C%":0,
        "D%":0,
        "F%":0,
        "Professor":"All"
    },
    {
        "GPA":4.0,
        "A%":100,
        "B%":0,
        "C%":0,
        "D%":0,
        "F%":0,
        "Professor":"Chernoff, Yury"
    },
    {
        "GPA":4.0,
        "A%":100,
        "B%":0,
        "C%":0,
        "D%":0,
        "F%":0,
        "Professor":"Choi, Jung"
    },
    {
        "GPA":4.0,
        "A%":100,
        "B%":0,
        "C%":0,
        "D%":0,
        "F%":0,
        "Professor":"Dusenbery, David"
    },
    {
        "GPA":4.0,
        "A%":100,
        "B%":0,
        "C%":0,
        "D%":0,
        "F%":0,
        "Professor":"Hall, Dwight"
    },
    {
        "GPA":4.0,
        "A%":100,
        "B%":0,
        "C%":0,
        "D%":0,
        "F%":0,
        "Professor":"Jouline, Igor"
    },
    {
        "GPA":4.0,
        "A%":100,
        "B%":0,
        "C%":0,
        "D%":0,
        "F%":0,
        "Professor":"Kirby, John"
    },
    {
        "GPA":4.0,
        "A%":100,
        "B%":0,
        "C%":0,
        "D%":0,
        "F%":0,
        "Professor":"Merrill, Alfred"
    },
    {
        "GPA":4.0,
        "A%":100,
        "B%":0,
        "C%":0,
        "D%":0,
        "F%":0,
        "Professor":"Montoya, Joseph"
    },
    {
        "GPA":4.0,
        "A%":100,
        "B%":0,
        "C%":0,
        "D%":0,
        "F%":0,
        "Professor":"Radhakrishna, Harish"
    },
    {
        "GPA":4.0,
        "A%":100,
        "B%":0,
        "C%":0,
        "D%":0,
        "F%":0,
        "Professor":"Weissburg, Marc"
    },
    {
        "GPA":4.0,
        "A%":100,
        "B%":0,
        "C%":0,
        "D%":0,
        "F%":0,
        "Professor":"Yen, Jeannette"
    }
]