[
    {
        "GPA":3.69,
        "A%":71,
        "B%":25,
        "C%":2,
        "D%":0,
        "F%":0,
        "Professor":"All"
    },
    {
        "GPA":3.67,
        "A%":69,
        "B%":25,
        "C%":4,
        "D%":0,
        "F%":0,
        "Professor":"Burgess, Robert"
    },
    {
        "GPA":3.48,
        "A%":50,
        "B%":48,
        "C%":2,
        "D%":0,
        "F%":0,
        "Professor":"Ghosh, Soumen"
    },
    {
        "GPA":3.95,
        "A%":96,
        "B%":3,
        "C%":1,
        "D%":0,
        "F%":0,
        "Professor":"Singhal, Vinod"
    }
]