[
    {
        "GPA":3.97,
        "A%":97,
        "B%":2,
        "C%":0,
        "D%":0,
        "F%":0,
        "Professor":"All"
    },
    {
        "GPA":3.95,
        "A%":95,
        "B%":4,
        "C%":1,
        "D%":0,
        "F%":0,
        "Professor":"Blum, Terry"
    },
    {
        "GPA":4.0,
        "A%":100,
        "B%":0,
        "C%":0,
        "D%":0,
        "F%":0,
        "Professor":"Mitra, Sabyasachi"
    },
    {
        "GPA":3.97,
        "A%":98,
        "B%":1,
        "C%":0,
        "D%":0,
        "F%":0,
        "Professor":"Zhang, Han"
    }
]