[
    {
        "GPA":3.7,
        "A%":72,
        "B%":25,
        "C%":2,
        "D%":0,
        "F%":0,
        "Professor":"All"
    },
    {
        "GPA":3.65,
        "A%":67,
        "B%":28,
        "C%":3,
        "D%":0,
        "F%":0,
        "Professor":"Choi, Young-Mi"
    },
    {
        "GPA":4.0,
        "A%":98,
        "B%":0,
        "C%":0,
        "D%":0,
        "F%":0,
        "Professor":"Mullick, Abir"
    },
    {
        "GPA":3.97,
        "A%":97,
        "B%":3,
        "C%":0,
        "D%":0,
        "F%":0,
        "Professor":"Stehle, Craig"
    }
]